rules_engine/__init__.py
rules_engine/py.typed
rules_engine-0.3.0.dist-info/LICENSE.txt
rules_engine-0.3.0.dist-info/METADATA
rules_engine-0.3.0.dist-info/WHEEL
rules_engine-0.3.0.dist-info/top_level.txt
rules_engine-0.3.0.dist-info/RECORD
