Metadata-Version: 2.1
Name: rules-engine
Version: 0.3.0
Summary: Rules engine
Home-page: https://github.com/fyndiq/rules-engine
Author: Fyndiq AB
Author-email: support@fyndiq.com
Project-URL: Bug Tracker, https://github.com/fyndiq/rules-engine/issues
Classifier: Programming Language :: Python :: 3
Requires-Python: >=3.6
License-File: LICENSE.txt
